README.rst
setup.py
hps/__init__.py
hps/clients/__init__.py
hps/clients/python/__init__.py
hps/clients/python/socket_client.py
hps/clients/python/zmq_client.py
hps/servers/__init__.py
hps/servers/base.py
hps/servers/socket_server.py
hps/servers/zmq_server.py
hps_nyu.egg-info/PKG-INFO
hps_nyu.egg-info/SOURCES.txt
hps_nyu.egg-info/dependency_links.txt
hps_nyu.egg-info/requires.txt
hps_nyu.egg-info/top_level.txt