Metadata-Version: 1.1
Name: hps-nyu
Version: 1.0.0
Summary: Tools for architecture for HPS games
Home-page: https://gitlab.com/mmc691/hps-project
Author: Team Rocket
Author-email: mmc691@nyu.edu
License: MIT
Download-URL: https://gitlab.com/mmc691/hps-project/
Platform: Linux
Platform: MacOS
Platform: Windows
Classifier: Development Status :: 5 - Production/Stable
Classifier: License :: OSI Approved :: MIT License
Classifier: Operating System :: Microsoft :: Windows
Classifier: Operating System :: MacOS
Classifier: Operating System :: POSIX
Classifier: Programming Language :: Python :: 3.5
Classifier: Programming Language :: Python :: 3.6
Classifier: Programming Language :: C++
Classifier: Programming Language :: Java
Classifier: Topic :: Games/Entertainment :: Puzzle Games
Classifier: Topic :: Games/Entertainment :: Turn Based Strategy
Classifier: Topic :: Utilities
